tanchan/__init__.py
tanchan/doc_parse.py
tanchan/py.typed
tanchan/_internal/__init__.py
tanchan/_internal/localisation.py
tanchan/components/__init__.py
tanchan/components/buttons.py
tanchan/components/config.py
tanchan/components/eval.py
tanchan/components/help.py
tanchan-0.4.3.dist-info/LICENSE
tanchan-0.4.3.dist-info/WHEEL
tanchan-0.4.3.dist-info/METADATA
tanchan-0.4.3.dist-info/RECORD
