Metadata-Version: 2.3
Name: tanchan
Version: 0.4.3
Summary: A utility library which extends Tanjun.
Keywords: hikari
Author-email: Faster Speeding <lucina@lmbyrne.dev>
Requires-Python: >=3.11.0,<3.14
Classifier: Development Status :: 4 - Beta
Classifier: License :: OSI Approved :: BSD License
Classifier: Intended Audience :: Developers
Classifier: Natural Language :: English
Classifier: Operating System :: OS Independent
Classifier: Programming Language :: Python :: 3.11
Classifier: Programming Language :: Python :: 3.12
Classifier: Programming Language :: Python :: 3.13
Classifier: Programming Language :: Python :: Implementation :: CPython
Classifier: Topic :: Communications :: Chat
Classifier: Topic :: Software Development :: Libraries
Classifier: Topic :: Software Development :: Libraries :: Python Modules
Classifier: Topic :: Utilities
Classifier: Typing :: Typed
Requires-Dist: hikari-tanjun>=2.16, <3
Requires-Dist: typing-extensions>=4.5, <5
Requires-Dist: hikari-yuyo>=1.18.0, <2 ; extra == "yuyo"
Project-URL: Changelog, https://github.com/FasterSpeeding/tan-chan/blob/master/CHANGELOG.md
Project-URL: Documentation, https://tan-chan.cursed.solutions/
Project-URL: Homepage, https://github.com/FasterSpeeding/Tan-chan
Project-URL: Repository, https://github.com/FasterSpeeding/Tan-chan
Provides-Extra: yuyo
